[{"feature_name":["transaction_mismatch","fee_ratio","success_rate","log_cosmos_total_gas_used","log_evm_gas_growth","cosmos_new_block","evm_new_block","gas_efficiency","block_sync_ratio","fee_inconsistency","cross_chain_disparity","gas_usage_anomaly","isolation_score","trans_volatility","fee_volatility"],"feature_mean":{"transaction_mismatch":-0.36,"fee_ratio":-15.1674425865,"success_rate":-0.1993129326,"log_cosmos_total_gas_used":1.3503029856,"log_evm_gas_growth":-0.36,"cosmos_new_block":8500.0,"evm_new_block":0.1632239323,"gas_efficiency":-0.2693087888,"block_sync_ratio":-0.404522149,"fee_inconsistency":0.2412866913,"cross_chain_disparity":-0.36,"gas_usage_anomaly":-0.36,"isolation_score":0.1,"trans_volatility":0.2283665782,"fee_volatility":0.5546673968},"feature_std":{"transaction_mismatch":0.4848732214,"fee_ratio":59.797188942,"success_rate":0.4490301436,"log_cosmos_total_gas_used":5.4054092408,"log_evm_gas_growth":0.4848732214,"cosmos_new_block":39087.8564894364,"evm_new_block":0.4668731095,"gas_efficiency":0.4690547109,"block_sync_ratio":0.4871328978,"fee_inconsistency":0.4706954041,"cross_chain_disparity":0.4848732214,"gas_usage_anomaly":0.4848732214,"isolation_score":0.3030457634,"trans_volatility":0.8171310902,"fee_volatility":2.1084619896},"feature_min":{"transaction_mismatch":-1.0,"fee_ratio":-262.8925679399,"success_rate":-0.7790169468,"log_cosmos_total_gas_used":0.0,"log_evm_gas_growth":-1.0,"cosmos_new_block":0.0,"evm_new_block":-0.3365818578,"gas_efficiency":-0.8831333814,"block_sync_ratio":-1.0,"fee_inconsistency":-0.2777118528,"cross_chain_disparity":-1.0,"gas_usage_anomaly":-1.0,"isolation_score":0.0,"trans_volatility":-0.4102435483,"fee_volatility":-0.4235092986},"feature_max":{"transaction_mismatch":0.0,"fee_ratio":0.6676372236,"success_rate":0.2394904741,"log_cosmos_total_gas_used":23.3476232268,"log_evm_gas_growth":0.0,"cosmos_new_block":207735.0,"evm_new_block":0.7224164381,"gas_efficiency":0.2148141914,"block_sync_ratio":0.0,"fee_inconsistency":0.8245815634,"cross_chain_disparity":0.0,"gas_usage_anomaly":0.0,"isolation_score":1.0,"trans_volatility":3.9578643585,"fee_volatility":11.7691890859}}]